{
  "kind": "singleType",
  "collectionName": "general_infos",
  "info": {
    "singularName": "general-info",
    "pluralName": "general-infos",
    "displayName": "General Info"
  },
  "options": {
    "draftAndPublish": true
  },
  "pluginOptions": {},
  "attributes": {
    "DayLogo": {
      "type": "media",
      "multiple": false,
      "allowedTypes": [
        "images"
      ]
    },
    "NightLogo": {
      "type": "media",
      "multiple": false,
      "allowedTypes": [
        "images"
      ]
    },
    "Rights": {
      "type": "string",
      "required": true,
      "unique": true
    }
  }
}
